deep_research_client/__init__.py
deep_research_client/_version.py
deep_research_client/cache.py
deep_research_client/cli.py
deep_research_client/client.py
deep_research_client/formatter.py
deep_research_client/markdown_parser.py
deep_research_client/model_cards.py
deep_research_client/models.py
deep_research_client/provider_params.py
deep_research_client/system_prompts.py
deep_research_client/templates.py
deep_research_client/processing/__init__.py
deep_research_client/processing/processor.py
deep_research_client/processing/result_formatter.py
deep_research_client/processing/template_processor.py
deep_research_client/providers/__init__.py
deep_research_client/providers/consensus.py
deep_research_client/providers/cyberian.py
deep_research_client/providers/falcon.py
deep_research_client/providers/mock.py
deep_research_client/providers/openai.py
deep_research_client/providers/perplexity.py
deep_research_client/templates/research_result.html.j2
deep_research_client/workflows/__init__.py
deep_research_client/workflows/deep-research.yaml
deep_research_client-0.1.6.dist-info/METADATA
deep_research_client-0.1.6.dist-info/WHEEL
deep_research_client-0.1.6.dist-info/entry_points.txt
deep_research_client-0.1.6.dist-info/RECORD
