Metadata-Version: 2.4
Name: deep_research_client
Version: 0.1.6
Summary: Wrapper for multiple deep research tools
Author-email: My Name <my-name@my-org.org>
License-Expression: BSD-3-Clause
Requires-Python: <4.0,>=3.12
Requires-Dist: aiofiles>=23.0.0
Requires-Dist: edison-client>=0.7.7.dev70
Requires-Dist: httpx>=0.28.1
Requires-Dist: jinja2>=3.1.6
Requires-Dist: openai>=2.0.0
Requires-Dist: pydantic>=2.0.0
Requires-Dist: pyyaml>=6.0
Requires-Dist: typer>=0.9.0
Provides-Extra: cyberian
Requires-Dist: cyberian>=0.2.0; extra == 'cyberian'
